algorithm/__init__.py
algorithm/hello.py
algorithm/models.py
algorithm/split.py
gamawu-0.1.6.dist-info/METADATA
gamawu-0.1.6.dist-info/WHEEL
gamawu-0.1.6.dist-info/top_level.txt
gamawu-0.1.6.dist-info/RECORD
